gridwiz_analytics/__init__.py
gridwiz_analytics/core.py
gridwiz_analytics-0.1.0.dist-info/METADATA
gridwiz_analytics-0.1.0.dist-info/WHEEL
gridwiz_analytics-0.1.0.dist-info/licenses/LICENSE
gridwiz_analytics-0.1.0.dist-info/RECORD
