Metadata-Version: 2.4
Name: gridwiz_analytics
Version: 0.1.0
Summary: Data analysis utilities for GridWiz (extracted from notebook)
Project-URL: Homepage, https://example.com/gridwiz
Author: GridWiz Team
License: MIT
License-File: LICENSE
Keywords: analysis,analytics,data,gridwiz
Classifier: Intended Audience :: Developers
Classifier: License :: OSI Approved :: MIT License
Classifier: Programming Language :: Python :: 3
Classifier: Topic :: Scientific/Engineering :: Information Analysis
Requires-Python: >=3.8
Requires-Dist: matplotlib<3.8,>=3.7
Requires-Dist: numpy<2.0,>=1.24
Requires-Dist: openpyxl>=3.1
Requires-Dist: pandas<2.2,>=2.0
